[
    {
        "countryId": "ID",
        "provinceId": "11",
        "cityId": "32",
        "districtId": "12",
        "subDistrictId": "12",
        "postalCode": "61216",
        "longitude": 0.0,
        "latitude": 0.0,
        "desa": "Panjunan",
        "kecamatan": "Sukodono",
        "kota": "Sidoarjo",
        "alamat": "RT.5/RW.14 JM8J+5JW, Babatan, Panjunan, Kec. Sukodono, Kabupaten Sidoarjo, Jawa Timur 61258, Indonesia"
    },
    {
        "countryId": "ID",
        "provinceId": "11",
        "cityId": "32",
        "districtId": "12",
        "subDistrictId": "17",
        "postalCode": "61258",
        "longitude": 0.0,
        "latitude": 0.0,
        "desa": "Sukodono",
        "kecamatan": "Sukodono",
        "kota": "Sidoarjo",
        "alamat": "RT.7/RW.4 Jl. Ketapang - Suko No.20, Dusun Ketapang, Suko, Kec. Sukodono, Kabupaten Sidoarjo, Jawa Timur 61258, Indonesia"
    },
    {
        "countryId": "ID",
        "provinceId": "11",
        "cityId": "32",
        "districtId": "12",
        "subDistrictId": "16",
        "postalCode": "61258",
        "longitude": 0.0,
        "latitude": 0.0,
        "desa": "Suko",
        "kecamatan": "Sukodono",
        "kota": "Sidoarjo",
        "alamat": "RT.7/RW.4 Jl. Ketapang - Suko No.20, Dusun Ketapang, Suko, Kec. Sukodono, Kabupaten Sidoarjo, Jawa Timur 61258, Indonesia"
    },
    {
        "countryId": "ID",
        "provinceId": "11",
        "cityId": "32",
        "districtId": "12",
        "subDistrictId": "17",
        "postalCode": "61258",
        "longitude": 0.0,
        "latitude": 0.0,
        "desa": "Sukodono",
        "kecamatan": "Sukodono",
        "kota": "Sidoarjo",
        "alamat": "RT.4/RW.8 Sukodono,dungus rt13, Dungus, Sukodono, Kec. Sukodono, Kabupaten Sidoarjo, Jawa Timur 61258, Indonesia"
    },
    {
        "countryId": "ID",
        "provinceId": "11",
        "cityId": "32",
        "districtId": "12",
        "subDistrictId": "13",
        "postalCode": "61258",
        "longitude": 0.0,
        "latitude": 0.0,
        "desa": "Pekarungan",
        "kecamatan": "Sukodono",
        "kota": "Sidoarjo",
        "alamat": "RT.1/RW.13 HMV8+7PG, Pekorungan, Pekarungan, Kec. Sukodono, Kabupaten Sidoarjo, Jawa Timur 61258, Indonesia"
    },
    {
        "countryId": "ID",
        "provinceId": "11",
        "cityId": "32",
        "districtId": "12",
        "subDistrictId": "6",
        "postalCode": "61258",
        "longitude": 0.0,
        "latitude": 0.0,
        "desa": "Kebonagung",
        "kecamatan": "Sukodono",
        "kota": "Sidoarjo",
        "alamat": "RT.8/RW.1 HMMG+QR3, Sambang, Kebonagung, Kec. Sukodono, Kabupaten Sidoarjo, Jawa Timur 61258, Indonesia"
    },
    {
        "countryId": "ID",
        "provinceId": "11",
        "cityId": "32",
        "districtId": "12",
        "subDistrictId": "18",
        "postalCode": "61258",
        "longitude": 0.0,
        "latitude": 0.0,
        "desa": "Suruh",
        "kecamatan": "Sukodono",
        "kota": "Sidoarjo",
        "alamat": "HMVJ+955, RT.04/RW.01, Prumpon, Suruh, Kec. Sukodono, Kabupaten Sidoarjo, Jawa Timur 61258, Indonesia"
    },
    {
        "countryId": "ID",
        "provinceId": "11",
        "cityId": "32",
        "districtId": "12",
        "subDistrictId": "17",
        "postalCode": "61258",
        "longitude": 0.0,
        "latitude": 0.0,
        "desa": "Sukodono",
        "kecamatan": "Sukodono",
        "kota": "Sidoarjo",
        "alamat": "RT.9/RW.2 Jl. Sidopurno No.270, Sukadono, Sukodono, Kec. Sukodono, Kabupaten Sidoarjo, Jawa Timur 61258, Indonesia"
    },
    {
        "countryId": "ID",
        "provinceId": "11",
        "cityId": "32",
        "districtId": "12",
        "subDistrictId": "17",
        "postalCode": "61258",
        "longitude": 0.0,
        "latitude": 0.0,
        "desa": "Sukodono",
        "kecamatan": "Sukodono",
        "kota": "Sidoarjo",
        "alamat": "RT.8/RW.12 Jl. Ketapang - Suko No.25, Dusun Ketapang, Suko, Kec. Sukodono, Kabupaten Sidoarjo, Jawa Timur 61258, Indonesia"
    },
    {
        "countryId": "ID",
        "provinceId": "11",
        "cityId": "32",
        "districtId": "12",
        "subDistrictId": "16",
        "postalCode": "61258",
        "longitude": 0.0,
        "latitude": 0.0,
        "desa": "Suko",
        "kecamatan": "Sukodono",
        "kota": "Sidoarjo",
        "alamat": "RT.8/RW.12 Jl. Ketapang - Suko No.25, Dusun Ketapang, Suko, Kec. Sukodono, Kabupaten Sidoarjo, Jawa Timur 61258, Indonesia"
    },
    {
        "countryId": "ID",
        "provinceId": "11",
        "cityId": "32",
        "districtId": "12",
        "subDistrictId": "17",
        "postalCode": "61258",
        "longitude": 0.0,
        "latitude": 0.0,
        "desa": "Sukodono",
        "kecamatan": "Sukodono",
        "kota": "Sidoarjo",
        "alamat": "RT.1/RW.1 Jl. Raya Dungus No.20b, Sukadono, Sukodono, Kec. Sukodono, Kabupaten Sidoarjo, Jawa Timur 61258, Indonesia"
    },
    {
        "countryId": "ID",
        "provinceId": "11",
        "cityId": "32",
        "districtId": "12",
        "subDistrictId": "17",
        "postalCode": "61258",
        "longitude": 0.0,
        "latitude": 0.0,
        "desa": "Sukodono",
        "kecamatan": "Sukodono",
        "kota": "Sidoarjo",
        "alamat": "RT.5/RW.13 Jl. Raya Dungus No.20b, Sukadono, Sukodono, Kec. Sukodono, Kabupaten Sidoarjo, Jawa Timur 61258, Indonesia"
    },
    {
        "countryId": "ID",
        "provinceId": "11",
        "cityId": "32",
        "districtId": "12",
        "subDistrictId": "5",
        "postalCode": "61258",
        "longitude": 0.0,
        "latitude": 0.0,
        "desa": "Jumputrejo",
        "kecamatan": "Sukodono",
        "kota": "Sidoarjo",
        "alamat": "RT.6/RW.7 HMMX+58G, Unnamed Road, Beciro, Jumputrejo, Kec. Sukodono, Kabupaten Sidoarjo, Jawa Timur 61258, Indonesia"
    },
    {
        "countryId": "ID",
        "provinceId": "11",
        "cityId": "32",
        "districtId": "12",
        "subDistrictId": "12",
        "postalCode": "61216",
        "longitude": 0.0,
        "latitude": 0.0,
        "desa": "Panjunan",
        "kecamatan": "Sukodono",
        "kota": "Sidoarjo",
        "alamat": "RT.5/RW.12 JM8G+W63, Babatan, Panjunan, Kec. Sukodono, Kabupaten Sidoarjo, Jawa Timur 61258, Indonesia"
    },
    {
        "countryId": "ID",
        "provinceId": "11",
        "cityId": "32",
        "districtId": "12",
        "subDistrictId": "1",
        "postalCode": "61258",
        "longitude": 0.0,
        "latitude": 0.0,
        "desa": "Anggaswangi",
        "kecamatan": "Sukodono",
        "kota": "Sidoarjo",
        "alamat": "RT.5/RW.7 HMHP+5GQ, Jl. Putra Bangsa, Kweni, Anggaswangi, Kec. Sukodono, Kabupaten Sidoarjo, Jawa Timur 61258, Indonesia"
    },
    {
        "countryId": "ID",
        "provinceId": "11",
        "cityId": "32",
        "districtId": "12",
        "subDistrictId": "17",
        "postalCode": "61258",
        "longitude": 0.0,
        "latitude": 0.0,
        "desa": "Sukodono",
        "kecamatan": "Sukodono",
        "kota": "Sidoarjo",
        "alamat": "RT.6/RW.10 kost di belakang perumahan, kost ijo pak suroto, Jl. Permata Sukodono Raya, Sukodono, Kec. Sukodono, Kabupaten Sidoarjo, Jawa Timur, Indonesia"
    },
    {
        "countryId": "ID",
        "provinceId": "11",
        "cityId": "32",
        "districtId": "12",
        "subDistrictId": "5",
        "postalCode": "61258",
        "longitude": 0.0,
        "latitude": 0.0,
        "desa": "Jumputrejo",
        "kecamatan": "Sukodono",
        "kota": "Sidoarjo",
        "alamat": "RT.4/RW.1 beciro rt 04 rw 01, Beciro, Jumputrejo, Sukodono, Sidoarjo Regency, East Java 61258, Indonesia"
    },
    {
        "countryId": "ID",
        "provinceId": "11",
        "cityId": "32",
        "districtId": "12",
        "subDistrictId": "17",
        "postalCode": "61258",
        "longitude": 0.0,
        "latitude": 0.0,
        "desa": "Sukodono",
        "kecamatan": "Sukodono",
        "kota": "Sidoarjo",
        "alamat": "RT.9/RW.2 JM7H+77F, Dungus, Sukodono, Kec. Sukodono, Kabupaten Sidoarjo, Jawa Timur 61258, Indonesia"
    },
    {
        "countryId": "ID",
        "provinceId": "11",
        "cityId": "32",
        "districtId": "12",
        "subDistrictId": "13",
        "postalCode": "61258",
        "longitude": 0.0,
        "latitude": 0.0,
        "desa": "Pekarungan",
        "kecamatan": "Sukodono",
        "kota": "Sidoarjo",
        "alamat": "RT.6/RW.12 HMW8+5W6, Jl. Gubuk, Pekorungan, Pekarungan, Kec. Sukodono, Kabupaten Sidoarjo, Jawa Timur 61258, Indonesia"
    },
    {
        "countryId": "ID",
        "provinceId": "11",
        "cityId": "32",
        "districtId": "12",
        "subDistrictId": "17",
        "postalCode": "61258",
        "longitude": 0.0,
        "latitude": 0.0,
        "desa": "Sukodono",
        "kecamatan": "Sukodono",
        "kota": "Sidoarjo",
        "alamat": "Dungus, RT.19/RW.05, Sukadono, Sukodono, Kec. Sukodono, Kabupaten Sidoarjo, Jawa Timur 61258, Indonesia"
    },
    {
        "countryId": "ID",
        "provinceId": "11",
        "cityId": "32",
        "districtId": "12",
        "subDistrictId": "17",
        "postalCode": "61258",
        "longitude": 0.0,
        "latitude": 0.0,
        "desa": "Sukodono",
        "kecamatan": "Sukodono",
        "kota": "Sidoarjo",
        "alamat": "Kavling Sukodono Blok K 17 RT01 RW01, Sawo, Sukodono, Kec. Sukodono, Kabupaten Sidoarjo, Jawa Timur 61258, Indonesia"
    },
    {
        "countryId": "ID",
        "provinceId": "11",
        "cityId": "32",
        "districtId": "12",
        "subDistrictId": "17",
        "postalCode": "61258",
        "longitude": 0.0,
        "latitude": 0.0,
        "desa": "Sukodono",
        "kecamatan": "Sukodono",
        "kota": "Sidoarjo",
        "alamat": "RT.2/RW.3 JM3G+25F, Sukadono, Sukodono, Kec. Sukodono, Kabupaten Sidoarjo, Jawa Timur 61258, Indonesia"
    },
    {
        "countryId": "ID",
        "provinceId": "11",
        "cityId": "32",
        "districtId": "12",
        "subDistrictId": "6",
        "postalCode": "61258",
        "longitude": 0.0,
        "latitude": 0.0,
        "desa": "Kebonagung",
        "kecamatan": "Sukodono",
        "kota": "Sidoarjo",
        "alamat": "RT.1/RW.2 HMHJ+784, Unnamed Road, Sambang, Kebonagung, Kec. Sukodono, Kabupaten Sidoarjo, Jawa Timur 61258, Indonesia"
    },
    {
        "countryId": "ID",
        "provinceId": "11",
        "cityId": "32",
        "districtId": "12",
        "subDistrictId": "18",
        "postalCode": "61258",
        "longitude": 0.0,
        "latitude": 0.0,
        "desa": "Suruh",
        "kecamatan": "Sukodono",
        "kota": "Sidoarjo",
        "alamat": "HMRJ+J64, Jl. Guntur I, RT.10/RW.02, Prumpon, Suruh, Kec. Sukodono, Kabupaten Sidoarjo, Jawa Timur 61258, Indonesia"
    },
    {
        "countryId": "ID",
        "provinceId": "11",
        "cityId": "32",
        "districtId": "12",
        "subDistrictId": "13",
        "postalCode": "61258",
        "longitude": 0.0,
        "latitude": 0.0,
        "desa": "Pekarungan",
        "kecamatan": "Sukodono",
        "kota": "Sidoarjo",
        "alamat": "RT.8/RW.5 Jl. Imam Bonjol No.16, Karangnongko, Pekarungan, Kec. Sukodono, Kabupaten Sidoarjo, Jawa Timur 61258, Indonesia"
    },
    {
        "countryId": "ID",
        "provinceId": "11",
        "cityId": "32",
        "districtId": "12",
        "subDistrictId": "5",
        "postalCode": "61258",
        "longitude": 0.0,
        "latitude": 0.0,
        "desa": "Jumputrejo",
        "kecamatan": "Sukodono",
        "kota": "Sidoarjo",
        "alamat": "RT.2/RW.11 HMHW+89W, Beciro, Jumputrejo, Kec. Sukodono, Kabupaten Sidoarjo, Jawa Timur 61258, Indonesia"
    },
    {
        "countryId": "ID",
        "provinceId": "11",
        "cityId": "32",
        "districtId": "12",
        "subDistrictId": "1",
        "postalCode": "61258",
        "longitude": 0.0,
        "latitude": 0.0,
        "desa": "Anggaswangi",
        "kecamatan": "Sukodono",
        "kota": "Sidoarjo",
        "alamat": "RT.1/RW.11 HMHP+5GQ, Jl. Putra Bangsa, Kweni, Anggaswangi, Kec. Sukodono, Kabupaten Sidoarjo, Jawa Timur 61258, Indonesia"
    },
    {
        "countryId": "ID",
        "provinceId": "11",
        "cityId": "32",
        "districtId": "12",
        "subDistrictId": "2",
        "postalCode": "61258",
        "longitude": 0.0,
        "latitude": 0.0,
        "desa": "Bangsri",
        "kecamatan": "Sukodono",
        "kota": "Sidoarjo",
        "alamat": "RT.1/RW.5 JM4G+453, Gang depan balai desa, Sukadono, Bangsri, Kec. Sukodono, Kabupaten Sidoarjo, Jawa Timur 61258, Indonesia"
    },
    {
        "countryId": "ID",
        "provinceId": "11",
        "cityId": "32",
        "districtId": "12",
        "subDistrictId": "1",
        "postalCode": "61258",
        "longitude": 0.0,
        "latitude": 0.0,
        "desa": "Anggaswangi",
        "kecamatan": "Sukodono",
        "kota": "Sidoarjo",
        "alamat": "RT.1/RW.1 HMMM+G8M, Unnamed Road, Anggaswangi, Kec. Sukodono, Kabupaten Sidoarjo, Jawa Timur 61258, Indonesia"
    },
    {
        "countryId": "ID",
        "provinceId": "11",
        "cityId": "32",
        "districtId": "12",
        "subDistrictId": "17",
        "postalCode": "61258",
        "longitude": 0.0,
        "latitude": 0.0,
        "desa": "Sukodono",
        "kecamatan": "Sukodono",
        "kota": "Sidoarjo",
        "alamat": "RT.8/RW.11 kost di belakang perumahan, kost ijo pak suroto, Jl. Permata Sukodono Raya, Sukodono, Kec. Sukodono, Kabupaten Sidoarjo, Jawa Timur, Indonesia"
    },
    {
        "countryId": "ID",
        "provinceId": "11",
        "cityId": "32",
        "districtId": "12",
        "subDistrictId": "2",
        "postalCode": "61258",
        "longitude": 0.0,
        "latitude": 0.0,
        "desa": "Bangsri",
        "kecamatan": "Sukodono",
        "kota": "Sidoarjo",
        "alamat": "RT.6/RW.3 Area Sawah, Bangsri, Sukodono, Sidoarjo Regency, East Java 61258, Indonesia"
    },
    {
        "countryId": "ID",
        "provinceId": "11",
        "cityId": "32",
        "districtId": "12",
        "subDistrictId": "1",
        "postalCode": "61258",
        "longitude": 0.0,
        "latitude": 0.0,
        "desa": "Anggaswangi",
        "kecamatan": "Sukodono",
        "kota": "Sidoarjo",
        "alamat": "RT.9/RW.7 Kavling Area, Sambang, Anggaswangi, Kec. Sukodono, Kabupaten Sidoarjo, Jawa Timur 61258, Indonesia"
    },
    {
        "countryId": "ID",
        "provinceId": "11",
        "cityId": "32",
        "districtId": "12",
        "subDistrictId": "5",
        "postalCode": "61258",
        "longitude": 0.0,
        "latitude": 0.0,
        "desa": "Jumputrejo",
        "kecamatan": "Sukodono",
        "kota": "Sidoarjo",
        "alamat": "RT.3/RW.14 Jl. Beciro No.2 RW 1, Beciro, Jumputrejo, Kec. Sukodono, Kabupaten Sidoarjo, Jawa Timur 61258, Indonesia"
    },
    {
        "countryId": "ID",
        "provinceId": "11",
        "cityId": "32",
        "districtId": "12",
        "subDistrictId": "5",
        "postalCode": "61258",
        "longitude": 0.0,
        "latitude": 0.0,
        "desa": "Jumputrejo",
        "kecamatan": "Sukodono",
        "kota": "Sidoarjo",
        "alamat": "RT.4/RW.3 Jl. Beciro No.2 RW 1, Beciro, Jumputrejo, Kec. Sukodono, Kabupaten Sidoarjo, Jawa Timur 61258, Indonesia"
    },
    {
        "countryId": "ID",
        "provinceId": "11",
        "cityId": "32",
        "districtId": "12",
        "subDistrictId": "5",
        "postalCode": "61258",
        "longitude": 0.0,
        "latitude": 0.0,
        "desa": "Jumputrejo",
        "kecamatan": "Sukodono",
        "kota": "Sidoarjo",
        "alamat": "RT.3/RW.2 Jl. Beciro No.2 RW 1, Beciro, Jumputrejo, Kec. Sukodono, Kabupaten Sidoarjo, Jawa Timur 61258, Indonesia"
    }
]