[
    {
        "countryId": "ID",
        "provinceId": "11",
        "cityId": "6",
        "districtId": "9",
        "subDistrictId": "6",
        "postalCode": "62181",
        "longitude": 0.0,
        "latitude": 0.0,
        "desa": "Kapas",
        "kecamatan": "Kapas",
        "kota": "Bojonegoro",
        "alamat": "RT.1/RW.13 RW4M+676, Guyangan, Kapas, Kec. Kapas, Kabupaten Bojonegoro, Jawa Timur 62181, Indonesia"
    },
    {
        "countryId": "ID",
        "provinceId": "11",
        "cityId": "6",
        "districtId": "9",
        "subDistrictId": "1",
        "postalCode": "62181",
        "longitude": 0.0,
        "latitude": 0.0,
        "desa": "Bakalan",
        "kecamatan": "Kapas",
        "kota": "Bojonegoro",
        "alamat": "RT.3/RW.8 RWCG+RGH, Ngaglik, Bakalan, Kec. Kapas, Kabupaten Bojonegoro, Jawa Timur 62181, Indonesia"
    },
    {
        "countryId": "ID",
        "provinceId": "11",
        "cityId": "6",
        "districtId": "9",
        "subDistrictId": "17",
        "postalCode": "62181",
        "longitude": 0.0,
        "latitude": 0.0,
        "desa": "Sukowati",
        "kecamatan": "Kapas",
        "kota": "Bojonegoro",
        "alamat": "RT.6/RW.5 Jl. Raya Sukowati No.267, Losari, Sukowati, Kec. Kapas, Kabupaten Bojonegoro, Jawa Timur 62181, Indonesia"
    },
    {
        "countryId": "ID",
        "provinceId": "11",
        "cityId": "6",
        "districtId": "9",
        "subDistrictId": "6",
        "postalCode": "62181",
        "longitude": 0.0,
        "latitude": 0.0,
        "desa": "Kapas",
        "kecamatan": "Kapas",
        "kota": "Bojonegoro",
        "alamat": "RT.5/RW.7 RW4H+RHJ, Guyangan, Kapas, Kec. Kapas, Kabupaten Bojonegoro, Jawa Timur 62181, Indonesia"
    },
    {
        "countryId": "ID",
        "provinceId": "11",
        "cityId": "6",
        "districtId": "9",
        "subDistrictId": "5",
        "postalCode": "62181",
        "longitude": 0.0,
        "latitude": 0.0,
        "desa": "Kalianyar",
        "kecamatan": "Kapas",
        "kota": "Bojonegoro",
        "alamat": "RT.8/RW.9 Jl. Dullah, Jeglongan, Kalianyar, Kec. Kapas, Kabupaten Bojonegoro, Jawa Timur 62181, Indonesia"
    },
    {
        "countryId": "ID",
        "provinceId": "11",
        "cityId": "6",
        "districtId": "9",
        "subDistrictId": "2",
        "postalCode": "62181",
        "longitude": 0.0,
        "latitude": 0.0,
        "desa": "Bangilan",
        "kecamatan": "Kapas",
        "kota": "Bojonegoro",
        "alamat": "RT.2/RW.13 RV4G+26G, Bangilan, Kec. Kapas, Kabupaten Bojonegoro, Jawa Timur 62181, Indonesia"
    },
    {
        "countryId": "ID",
        "provinceId": "11",
        "cityId": "6",
        "districtId": "9",
        "subDistrictId": "11",
        "postalCode": "62181",
        "longitude": 0.0,
        "latitude": 0.0,
        "desa": "Ngampel",
        "kecamatan": "Kapas",
        "kota": "Bojonegoro",
        "alamat": "RT.5/RW.11 RWV5+76Q, Sugihwaras, Ngampel, Kec. Kapas, Kabupaten Bojonegoro, Jawa Timur 62181, Indonesia"
    },
    {
        "countryId": "ID",
        "provinceId": "11",
        "cityId": "6",
        "districtId": "9",
        "subDistrictId": "6",
        "postalCode": "62181",
        "longitude": 0.0,
        "latitude": 0.0,
        "desa": "Kapas",
        "kecamatan": "Kapas",
        "kota": "Bojonegoro",
        "alamat": "RT.5/RW.13 RW3M+C4J, Kapas, Kec. Kapas, Kabupaten Bojonegoro, Jawa Timur 62181, Indonesia"
    },
    {
        "countryId": "ID",
        "provinceId": "11",
        "cityId": "6",
        "districtId": "9",
        "subDistrictId": "6",
        "postalCode": "62181",
        "longitude": 0.0,
        "latitude": 0.0,
        "desa": "Kapas",
        "kecamatan": "Kapas",
        "kota": "Bojonegoro",
        "alamat": "RW3M+F5C, Gg pencol, RT.20/RW.02, Kapas, Kec. Kapas, Kabupaten Bojonegoro, Jawa Timur, Indonesia"
    },
    {
        "countryId": "ID",
        "provinceId": "11",
        "cityId": "6",
        "districtId": "9",
        "subDistrictId": "20",
        "postalCode": "62181",
        "longitude": 0.0,
        "latitude": 0.0,
        "desa": "Tikusan",
        "kecamatan": "Kapas",
        "kota": "Bojonegoro",
        "alamat": "RT.9/RW.3 RWF3+CMV, Tikusan, Kec. Kapas, Kabupaten Bojonegoro, Jawa Timur 62181, Indonesia"
    },
    {
        "countryId": "ID",
        "provinceId": "11",
        "cityId": "6",
        "districtId": "9",
        "subDistrictId": "5",
        "postalCode": "62181",
        "longitude": 0.0,
        "latitude": 0.0,
        "desa": "Kalianyar",
        "kecamatan": "Kapas",
        "kota": "Bojonegoro",
        "alamat": "RT.8/RW.10 RVFW+2HR, Kalianyar, Kec. Kapas, Kabupaten Bojonegoro, Jawa Timur 62181, Indonesia"
    },
    {
        "countryId": "ID",
        "provinceId": "11",
        "cityId": "6",
        "districtId": "9",
        "subDistrictId": "19",
        "postalCode": "62181",
        "longitude": 0.0,
        "latitude": 0.0,
        "desa": "Tapelan",
        "kecamatan": "Kapas",
        "kota": "Bojonegoro",
        "alamat": "RT.4/RW.9 QVQH+VMG, Tapelan, Kec. Kapas, Kabupaten Bojonegoro, Jawa Timur 62181, Indonesia"
    },
    {
        "countryId": "ID",
        "provinceId": "11",
        "cityId": "6",
        "districtId": "9",
        "subDistrictId": "1",
        "postalCode": "62181",
        "longitude": 0.0,
        "latitude": 0.0,
        "desa": "Bakalan",
        "kecamatan": "Kapas",
        "kota": "Bojonegoro",
        "alamat": "RT.1/RW.13 RWHH+H54, Sambidono, Bakalan, Kec. Kapas, Kabupaten Bojonegoro, Jawa Timur 62181, Indonesia"
    },
    {
        "countryId": "ID",
        "provinceId": "11",
        "cityId": "6",
        "districtId": "9",
        "subDistrictId": "7",
        "postalCode": "62181",
        "longitude": 0.0,
        "latitude": 0.0,
        "desa": "Kedaton",
        "kecamatan": "Kapas",
        "kota": "Bojonegoro",
        "alamat": "RT.3/RW.4 QWXJ+H45, Kedaton, Kec. Kapas, Kabupaten Bojonegoro, Jawa Timur 62181, Indonesia"
    },
    {
        "countryId": "ID",
        "provinceId": "11",
        "cityId": "6",
        "districtId": "9",
        "subDistrictId": "10",
        "postalCode": "62181",
        "longitude": 0.0,
        "latitude": 0.0,
        "desa": "Mojodeso",
        "kecamatan": "Kapas",
        "kota": "Bojonegoro",
        "alamat": "RT.4/RW.7 RW7F+X67, Banaran Lor, Mojodeso, Kec. Kapas, Kabupaten Bojonegoro, Jawa Timur 62181, Indonesia"
    },
    {
        "countryId": "ID",
        "provinceId": "11",
        "cityId": "6",
        "districtId": "9",
        "subDistrictId": "17",
        "postalCode": "62181",
        "longitude": 0.0,
        "latitude": 0.0,
        "desa": "Sukowati",
        "kecamatan": "Kapas",
        "kota": "Bojonegoro",
        "alamat": "RT.8/RW.14 RW56+VW9, Ngeluk, Sukowati, Kec. Kapas, Kabupaten Bojonegoro, Jawa Timur 62181, Indonesia"
    },
    {
        "countryId": "ID",
        "provinceId": "11",
        "cityId": "6",
        "districtId": "9",
        "subDistrictId": "12",
        "postalCode": "62181",
        "longitude": 0.0,
        "latitude": 0.0,
        "desa": "Padang Mentoyo",
        "kecamatan": "Kapas",
        "kota": "Bojonegoro",
        "alamat": "RT.4/RW.13 QVVQ+J27, Sabrang Wetan, Padang Mentoyo, Kec. Kapas, Kabupaten Bojonegoro, Jawa Timur 62181, Indonesia"
    },
    {
        "countryId": "ID",
        "provinceId": "11",
        "cityId": "6",
        "districtId": "9",
        "subDistrictId": "3",
        "postalCode": "62181",
        "longitude": 0.0,
        "latitude": 0.0,
        "desa": "Bendo",
        "kecamatan": "Kapas",
        "kota": "Bojonegoro",
        "alamat": "RT.5/RW.12 QVMF+3RQ, Bendo, Kec. Kapas, Kabupaten Bojonegoro, Jawa Timur 62181, Indonesia"
    },
    {
        "countryId": "ID",
        "provinceId": "11",
        "cityId": "6",
        "districtId": "9",
        "subDistrictId": "13",
        "postalCode": "62181",
        "longitude": 0.0,
        "latitude": 0.0,
        "desa": "Plesungan",
        "kecamatan": "Kapas",
        "kota": "Bojonegoro",
        "alamat": "RW6H+FCG, RT.03/RW.01, Plesungan, Kec. Kapas, Kabupaten Bojonegoro, Jawa Timur 62181, Indonesia"
    },
    {
        "countryId": "ID",
        "provinceId": "11",
        "cityId": "6",
        "districtId": "9",
        "subDistrictId": "20",
        "postalCode": "62181",
        "longitude": 0.0,
        "latitude": 0.0,
        "desa": "Tikusan",
        "kecamatan": "Kapas",
        "kota": "Bojonegoro",
        "alamat": "RT.9/RW.7 Jl. Tikusan No.163, Tikusan, Kec. Kapas, Kabupaten Bojonegoro, Jawa Timur 62181, Indonesia"
    },
    {
        "countryId": "ID",
        "provinceId": "11",
        "cityId": "6",
        "districtId": "9",
        "subDistrictId": "21",
        "postalCode": "62181",
        "longitude": 0.0,
        "latitude": 0.0,
        "desa": "Wedi",
        "kecamatan": "Kapas",
        "kota": "Bojonegoro",
        "alamat": "RT.9/RW.7 RV5V+GJC, Unnamed Road, Wedi Kidul, Wedi, Kec. Kapas, Kabupaten Bojonegoro, Jawa Timur 62181, Indonesia"
    },
    {
        "countryId": "ID",
        "provinceId": "11",
        "cityId": "6",
        "districtId": "9",
        "subDistrictId": "8",
        "postalCode": "62181",
        "longitude": 0.0,
        "latitude": 0.0,
        "desa": "Klampok",
        "kecamatan": "Kapas",
        "kota": "Bojonegoro",
        "alamat": "RT.4/RW.1 Jl. Masuk No.112, Klampok, Kec. Kapas, Kabupaten Bojonegoro, Jawa Timur 62181, Indonesia"
    },
    {
        "countryId": "ID",
        "provinceId": "11",
        "cityId": "6",
        "districtId": "9",
        "subDistrictId": "5",
        "postalCode": "62181",
        "longitude": 0.0,
        "latitude": 0.0,
        "desa": "Kalianyar",
        "kecamatan": "Kapas",
        "kota": "Bojonegoro",
        "alamat": "RT.9/RW.12 RVFW+9GJ, Kalianyar, Kec. Kapas, Kabupaten Bojonegoro, Jawa Timur 62181, Indonesia"
    },
    {
        "countryId": "ID",
        "provinceId": "11",
        "cityId": "6",
        "districtId": "9",
        "subDistrictId": "15",
        "postalCode": "62181",
        "longitude": 0.0,
        "latitude": 0.0,
        "desa": "Sembung",
        "kecamatan": "Kapas",
        "kota": "Bojonegoro",
        "alamat": "Jl.Monginsidi Gg. Jagul RT/RW 04/01, Sembung, Kec. Kapas, Kabupaten Bojonegoro, Jawa Timur 62181, Indonesia"
    },
    {
        "countryId": "ID",
        "provinceId": "11",
        "cityId": "6",
        "districtId": "9",
        "subDistrictId": "1",
        "postalCode": "62181",
        "longitude": 0.0,
        "latitude": 0.0,
        "desa": "Bakalan",
        "kecamatan": "Kapas",
        "kota": "Bojonegoro",
        "alamat": "Ngaglik, RT.01 RW.01, Bakalan, Kapas, Ngaglik, Bakalan, Kec. Kapas, Kabupaten Bojonegoro, Jawa Timur 62181, Indonesia"
    },
    {
        "countryId": "ID",
        "provinceId": "11",
        "cityId": "6",
        "districtId": "9",
        "subDistrictId": "3",
        "postalCode": "62181",
        "longitude": 0.0,
        "latitude": 0.0,
        "desa": "Bendo",
        "kecamatan": "Kapas",
        "kota": "Bojonegoro",
        "alamat": "RT.4/RW.11 QV8F+9C4, Dukuhan Santren, Bendo, Kec. Kapas, Kabupaten Bojonegoro, Jawa Timur 62181, Indonesia"
    },
    {
        "countryId": "ID",
        "provinceId": "11",
        "cityId": "6",
        "districtId": "9",
        "subDistrictId": "11",
        "postalCode": "62181",
        "longitude": 0.0,
        "latitude": 0.0,
        "desa": "Ngampel",
        "kecamatan": "Kapas",
        "kota": "Bojonegoro",
        "alamat": "RT.2/RW.14 RWP3+9F3, Jl. Sukowati, Ngampel, Kapas, Ngampel, Kec. Kapas, Kabupaten Bojonegoro, Jawa Timur 62181, Indonesia"
    },
    {
        "countryId": "ID",
        "provinceId": "11",
        "cityId": "6",
        "districtId": "9",
        "subDistrictId": "3",
        "postalCode": "62181",
        "longitude": 0.0,
        "latitude": 0.0,
        "desa": "Bendo",
        "kecamatan": "Kapas",
        "kota": "Bojonegoro",
        "alamat": "RT.5/RW.9 QV89+2X8, Dukuhan Santren, Bendo, Kec. Kapas, Kabupaten Bojonegoro, Jawa Timur 62181, Indonesia"
    },
    {
        "countryId": "ID",
        "provinceId": "11",
        "cityId": "6",
        "districtId": "9",
        "subDistrictId": "7",
        "postalCode": "62181",
        "longitude": 0.0,
        "latitude": 0.0,
        "desa": "Kedaton",
        "kecamatan": "Kapas",
        "kota": "Bojonegoro",
        "alamat": "Jl setren, dusun setren RT.16, Jati Lor, Kedaton, Kec. Kapas, Kabupaten Bojonegoro, Jawa Timur 62182, Indonesia"
    },
    {
        "countryId": "ID",
        "provinceId": "11",
        "cityId": "6",
        "districtId": "9",
        "subDistrictId": "17",
        "postalCode": "62181",
        "longitude": 0.0,
        "latitude": 0.0,
        "desa": "Sukowati",
        "kecamatan": "Kapas",
        "kota": "Bojonegoro",
        "alamat": "RT.5/RW.5 RW56+3QF, Ngeluk, Sukowati, Kec. Kapas, Kabupaten Bojonegoro, Jawa Timur 62181, Indonesia"
    },
    {
        "countryId": "ID",
        "provinceId": "11",
        "cityId": "6",
        "districtId": "9",
        "subDistrictId": "4",
        "postalCode": "62181",
        "longitude": 0.0,
        "latitude": 0.0,
        "desa": "Bogo",
        "kecamatan": "Kapas",
        "kota": "Bojonegoro",
        "alamat": "RT.7/RW.8 RWJP+GV4, Unnamed Road, Bogo, Kec. Kapas, Kabupaten Bojonegoro, Jawa Timur 62181, Indonesia"
    },
    {
        "countryId": "ID",
        "provinceId": "11",
        "cityId": "6",
        "districtId": "9",
        "subDistrictId": "17",
        "postalCode": "62181",
        "longitude": 0.0,
        "latitude": 0.0,
        "desa": "Sukowati",
        "kecamatan": "Kapas",
        "kota": "Bojonegoro",
        "alamat": "RT.7/RW.13 RWF6+6Q4, Gg. Lkr., Sukolilo, Sukowati, Kec. Kapas, Kabupaten Bojonegoro, Jawa Timur 62181, Indonesia"
    },
    {
        "countryId": "ID",
        "provinceId": "11",
        "cityId": "6",
        "districtId": "9",
        "subDistrictId": "3",
        "postalCode": "62181",
        "longitude": 0.0,
        "latitude": 0.0,
        "desa": "Bendo",
        "kecamatan": "Kapas",
        "kota": "Bojonegoro",
        "alamat": "RT.3/RW.4 QV8F+Q88, Dukuhan Santren, Bendo, Kec. Kapas, Kabupaten Bojonegoro, Jawa Timur 62181, Indonesia"
    },
    {
        "countryId": "ID",
        "provinceId": "11",
        "cityId": "6",
        "districtId": "9",
        "subDistrictId": "21",
        "postalCode": "62181",
        "longitude": 0.0,
        "latitude": 0.0,
        "desa": "Wedi",
        "kecamatan": "Kapas",
        "kota": "Bojonegoro",
        "alamat": "RT.5/RW.14 RV7W+893, Wedi Lor, Wedi, Kec. Kapas, Kabupaten Bojonegoro, Jawa Timur 62181, Indonesia"
    },
    {
        "countryId": "ID",
        "provinceId": "11",
        "cityId": "6",
        "districtId": "9",
        "subDistrictId": "1",
        "postalCode": "62181",
        "longitude": 0.0,
        "latitude": 0.0,
        "desa": "Bakalan",
        "kecamatan": "Kapas",
        "kota": "Bojonegoro",
        "alamat": "RT.1/RW.4 RW.02, Sambidono, Bakalan, Kapas, Bojonegoro Regency, East Java 62181, Indonesia"
    },
    {
        "countryId": "ID",
        "provinceId": "11",
        "cityId": "6",
        "districtId": "9",
        "subDistrictId": "19",
        "postalCode": "62181",
        "longitude": 0.0,
        "latitude": 0.0,
        "desa": "Tapelan",
        "kecamatan": "Kapas",
        "kota": "Bojonegoro",
        "alamat": "RT.6/RW.11 QVVM+QVH, gang kluwih, Padang Mentoyo, Tapelan, Kec. Kapas, Kabupaten Bojonegoro, Jawa Timur 62181, Indonesia"
    },
    {
        "countryId": "ID",
        "provinceId": "11",
        "cityId": "6",
        "districtId": "9",
        "subDistrictId": "20",
        "postalCode": "62181",
        "longitude": 0.0,
        "latitude": 0.0,
        "desa": "Tikusan",
        "kecamatan": "Kapas",
        "kota": "Bojonegoro",
        "alamat": "Jalan Tikusan, Gang Sadimin RT.04/RW.02 Dukuh, Karanglo, Tikusan, Kec. Kapas, Kabupaten Bojonegoro, Jawa Timur 62181, Indonesia"
    },
    {
        "countryId": "ID",
        "provinceId": "11",
        "cityId": "6",
        "districtId": "9",
        "subDistrictId": "13",
        "postalCode": "62181",
        "longitude": 0.0,
        "latitude": 0.0,
        "desa": "Plesungan",
        "kecamatan": "Kapas",
        "kota": "Bojonegoro",
        "alamat": "RT.4/RW.7 RW4F+R89, Jl. Raya Surabaya, Plesungan, Kec. Kapas, Kabupaten Bojonegoro, Jawa Timur 62181, Indonesia"
    },
    {
        "countryId": "ID",
        "provinceId": "11",
        "cityId": "6",
        "districtId": "9",
        "subDistrictId": "12",
        "postalCode": "62181",
        "longitude": 0.0,
        "latitude": 0.0,
        "desa": "Padang Mentoyo",
        "kecamatan": "Kapas",
        "kota": "Bojonegoro",
        "alamat": "RT.7/RW.7 QVQP+W9H, Sabrang Wetan, Padang Mentoyo, Kec. Kapas, Kabupaten Bojonegoro, Jawa Timur 62181, Indonesia"
    },
    {
        "countryId": "ID",
        "provinceId": "11",
        "cityId": "6",
        "districtId": "9",
        "subDistrictId": "20",
        "postalCode": "62181",
        "longitude": 0.0,
        "latitude": 0.0,
        "desa": "Tikusan",
        "kecamatan": "Kapas",
        "kota": "Bojonegoro",
        "alamat": "RT.9/RW.2 RWJ4+2RX, Bojonegoro Permai, Tikusan, Kec. Kapas, Kabupaten Bojonegoro, Jawa Timur 62181, Indonesia"
    },
    {
        "countryId": "ID",
        "provinceId": "11",
        "cityId": "6",
        "districtId": "9",
        "subDistrictId": "1",
        "postalCode": "62181",
        "longitude": 0.0,
        "latitude": 0.0,
        "desa": "Bakalan",
        "kecamatan": "Kapas",
        "kota": "Bojonegoro",
        "alamat": "RT.8/RW.9 RWGH+CCR, Jl. Raya Bakalan, Bakalan, Kec. Kapas, Kabupaten Bojonegoro, Jawa Timur 62181, Indonesia"
    },
    {
        "countryId": "ID",
        "provinceId": "11",
        "cityId": "6",
        "districtId": "9",
        "subDistrictId": "20",
        "postalCode": "62181",
        "longitude": 0.0,
        "latitude": 0.0,
        "desa": "Tikusan",
        "kecamatan": "Kapas",
        "kota": "Bojonegoro",
        "alamat": "RT.5/RW.1 RWH4+P62, Perumahan Bomai, Jalan Tikusan, Kapas, Bojonegoro Permai, Tikusan, Kec. Kapas, Kabupaten Bojonegoro, Jawa Timur 62181, Indonesia"
    },
    {
        "countryId": "ID",
        "provinceId": "11",
        "cityId": "6",
        "districtId": "9",
        "subDistrictId": "8",
        "postalCode": "62181",
        "longitude": 0.0,
        "latitude": 0.0,
        "desa": "Klampok",
        "kecamatan": "Kapas",
        "kota": "Bojonegoro",
        "alamat": "RT.8/RW.10 RW88+4XJ, Klampok, Kec. Kapas, Kabupaten Bojonegoro, Jawa Timur 62181, Indonesia"
    },
    {
        "countryId": "ID",
        "provinceId": "11",
        "cityId": "6",
        "districtId": "9",
        "subDistrictId": "7",
        "postalCode": "62181",
        "longitude": 0.0,
        "latitude": 0.0,
        "desa": "Kedaton",
        "kecamatan": "Kapas",
        "kota": "Bojonegoro",
        "alamat": "QWXJ+4M7, RT.07/RW.01, Kedaton, Kec. Kapas, Kabupaten Bojonegoro, Jawa Timur 62181, Indonesia"
    },
    {
        "countryId": "ID",
        "provinceId": "11",
        "cityId": "6",
        "districtId": "9",
        "subDistrictId": "7",
        "postalCode": "62181",
        "longitude": 0.0,
        "latitude": 0.0,
        "desa": "Kedaton",
        "kecamatan": "Kapas",
        "kota": "Bojonegoro",
        "alamat": "QWXG+CWF, Gg. Tembus, RT.10/RW.2, Kedaton, Kec. Kapas, Kabupaten Bojonegoro, Jawa Timur 62181, Indonesia"
    },
    {
        "countryId": "ID",
        "provinceId": "11",
        "cityId": "6",
        "districtId": "9",
        "subDistrictId": "4",
        "postalCode": "62181",
        "longitude": 0.0,
        "latitude": 0.0,
        "desa": "Bogo",
        "kecamatan": "Kapas",
        "kota": "Bojonegoro",
        "alamat": "RT.4/RW.12 RWPQ+3QR, Unnamed Road, Jati, Bogo, Kec. Kapas, Kabupaten Bojonegoro, Jawa Timur 62181, Indonesia"
    }
]