[
    {
        "countryId": "ID",
        "provinceId": "11",
        "cityId": "6",
        "districtId": "7",
        "subDistrictId": "5",
        "postalCode": "62152",
        "longitude": 0.0,
        "latitude": 0.0,
        "desa": "Kalitidu",
        "kecamatan": "Kalitidu",
        "kota": "Bojonegoro",
        "alamat": "RT.2/RW.1 VQ88+Q73, Gangsalan, Kalitidu, Kec. Kalitidu, Kabupaten Bojonegoro, Jawa Timur 62152, Indonesia"
    },
    {
        "countryId": "ID",
        "provinceId": "11",
        "cityId": "6",
        "districtId": "1",
        "subDistrictId": "4",
        "postalCode": "62111",
        "longitude": 0.0,
        "latitude": 0.0,
        "desa": "Kadipaten",
        "kecamatan": "Bojonegoro",
        "kota": "Bojonegoro",
        "alamat": "RT.7/RW.10 Jl. Teuku Umar No.68, Kadipaten, Kec. Bojonegoro, Kabupaten Bojonegoro, Jawa Timur 62111, Indonesia"
    },
    {
        "countryId": "ID",
        "provinceId": "11",
        "cityId": "6",
        "districtId": "1",
        "subDistrictId": "8",
        "postalCode": "62111",
        "longitude": 0.0,
        "latitude": 0.0,
        "desa": "Kepatihan",
        "kecamatan": "Bojonegoro",
        "kota": "Bojonegoro",
        "alamat": "RT.6/RW.4 Jl. Panglima Sudirman No.25, Kepatihan, Kec. Bojonegoro, Kabupaten Bojonegoro, Jawa Timur 62111, Indonesia"
    },
    {
        "countryId": "ID",
        "provinceId": "11",
        "cityId": "6",
        "districtId": "7",
        "subDistrictId": "17",
        "postalCode": "62152",
        "longitude": 0.0,
        "latitude": 0.0,
        "desa": "Panjunan",
        "kecamatan": "Kalitidu",
        "kota": "Bojonegoro",
        "alamat": "RT.3/RW.13 Jl. Raya Ngasem - Kalitidu No.350, Krajan, Panjunan, Kec. Kalitidu, Kabupaten Bojonegoro, Jawa Timur 62152, Indonesia"
    },
    {
        "countryId": "ID",
        "provinceId": "11",
        "cityId": "6",
        "districtId": "1",
        "subDistrictId": "4",
        "postalCode": "62111",
        "longitude": 0.0,
        "latitude": 0.0,
        "desa": "Kadipaten",
        "kecamatan": "Bojonegoro",
        "kota": "Bojonegoro",
        "alamat": "RT.6/RW.12 Jl. Ks.Tubun No.15, Kadipaten, Kec. Bojonegoro, Kabupaten Bojonegoro, Jawa Timur 62111, Indonesia"
    },
    {
        "countryId": "ID",
        "provinceId": "11",
        "cityId": "6",
        "districtId": "1",
        "subDistrictId": "4",
        "postalCode": "62111",
        "longitude": 0.0,
        "latitude": 0.0,
        "desa": "Kadipaten",
        "kecamatan": "Bojonegoro",
        "kota": "Bojonegoro",
        "alamat": "RT.6/RW.6 Jl. Rajawali No.156-158, Bojonegoro, Kadipaten, Kec. Bojonegoro, Kabupaten Bojonegoro, Jawa Timur 62117, Indonesia"
    }
]