[
    {
        "countryId": "ID",
        "provinceId": "11",
        "cityId": "11",
        "districtId": "4",
        "subDistrictId": "5",
        "postalCode": "64151",
        "longitude": 0.0,
        "latitude": 0.0,
        "desa": "Grogol",
        "kecamatan": "Grogol",
        "kota": "Kediri",
        "alamat": "6XW5+G49, Jl. Jawa Bedrek Selatan Grogol Kediri, RT.02/RW.01, Budrek Utara, Grogol, Kec. Grogol, Kabupaten Kediri, Jawa Timur 64151, Indonesia"
    },
    {
        "countryId": "ID",
        "provinceId": "11",
        "cityId": "11",
        "districtId": "4",
        "subDistrictId": "5",
        "postalCode": "64151",
        "longitude": 0.0,
        "latitude": 0.0,
        "desa": "Grogol",
        "kecamatan": "Grogol",
        "kota": "Kediri",
        "alamat": "Jl. Jawa Bedrek Selatan Grogol Kediri, RT.02/RW.03, Bedrek Selatan, Budrek Selatan, Grogol, Kec. Grogol, Kabupaten Kediri, Jawa Timur 64151, Indonesia"
    },
    {
        "countryId": "ID",
        "provinceId": "11",
        "cityId": "11",
        "districtId": "4",
        "subDistrictId": "2",
        "postalCode": "64151",
        "longitude": 0.0,
        "latitude": 0.0,
        "desa": "Cerme",
        "kecamatan": "Grogol",
        "kota": "Kediri",
        "alamat": "7X58+H26, Jl. Mangga Gg. 5, RT.19/RW.09, Gringging, Cerme, Grogol, Kediri Regency, East Java 64151, Indonesia"
    },
    {
        "countryId": "ID",
        "provinceId": "11",
        "cityId": "11",
        "districtId": "4",
        "subDistrictId": "5",
        "postalCode": "64151",
        "longitude": 0.0,
        "latitude": 0.0,
        "desa": "Grogol",
        "kecamatan": "Grogol",
        "kota": "Kediri",
        "alamat": "RT.4/RW.9 7X26+P6G, Griging Kidul, Grogol, Kec. Grogol, Kabupaten Kediri, Jawa Timur 64151, Indonesia"
    },
    {
        "countryId": "ID",
        "provinceId": "11",
        "cityId": "11",
        "districtId": "4",
        "subDistrictId": "5",
        "postalCode": "64151",
        "longitude": 0.0,
        "latitude": 0.0,
        "desa": "Grogol",
        "kecamatan": "Grogol",
        "kota": "Kediri",
        "alamat": "RT.1/RW.9 Jl. Jawa Bedrek Selatan Grogol Kediri, Budrek Utara, Grogol, Kec. Grogol, Kabupaten Kediri, Jawa Timur 64151, Indonesia"
    },
    {
        "countryId": "ID",
        "provinceId": "11",
        "cityId": "11",
        "districtId": "4",
        "subDistrictId": "5",
        "postalCode": "64151",
        "longitude": 0.0,
        "latitude": 0.0,
        "desa": "Grogol",
        "kecamatan": "Grogol",
        "kota": "Kediri",
        "alamat": "6XX5+PVG, Jl. Jawa Bedrek Selatan Grogol Kediri, RT.02/RW.02, Budrek Utara, Grogol, Kec. Grogol, Kabupaten Kediri, Jawa Timur 64151, Indonesia"
    },
    {
        "countryId": "ID",
        "provinceId": "11",
        "cityId": "11",
        "districtId": "4",
        "subDistrictId": "7",
        "postalCode": "64151",
        "longitude": 0.0,
        "latitude": 0.0,
        "desa": "Sonorejo",
        "kecamatan": "Grogol",
        "kota": "Kediri",
        "alamat": "RT.4/RW.13 7X4H+8FG, Sumbertowo, Sonorejo, Kec. Grogol, Kabupaten Kediri, Jawa Timur 64151, Indonesia"
    },
    {
        "countryId": "ID",
        "provinceId": "11",
        "cityId": "11",
        "districtId": "4",
        "subDistrictId": "5",
        "postalCode": "64151",
        "longitude": 0.0,
        "latitude": 0.0,
        "desa": "Grogol",
        "kecamatan": "Grogol",
        "kota": "Kediri",
        "alamat": "RT.2/RW.12 Jl. Jawa Bedrek Selatan Grogol Kediri, Budrek Selatan, Grogol, Kec. Grogol, Kabupaten Kediri, Jawa Timur 64151, Indonesia"
    },
    {
        "countryId": "ID",
        "provinceId": "11",
        "cityId": "11",
        "districtId": "4",
        "subDistrictId": "9",
        "postalCode": "64151",
        "longitude": 0.0,
        "latitude": 0.0,
        "desa": "Wonoasri",
        "kecamatan": "Grogol",
        "kota": "Kediri",
        "alamat": "RT.2/RW.13 Jl. Raya Wonoasri No.86, Sukosewu, Wonoasri, Kec. Grogol, Kabupaten Kediri, Jawa Timur 64152, Indonesia"
    },
    {
        "countryId": "ID",
        "provinceId": "11",
        "cityId": "11",
        "districtId": "4",
        "subDistrictId": "7",
        "postalCode": "64151",
        "longitude": 0.0,
        "latitude": 0.0,
        "desa": "Sonorejo",
        "kecamatan": "Grogol",
        "kota": "Kediri",
        "alamat": "RT.6/RW.5 7X2F+6R2, Sumbergambi Kidul, Sonorejo, Kec. Grogol, Kabupaten Kediri, Jawa Timur 64151, Indonesia"
    },
    {
        "countryId": "ID",
        "provinceId": "11",
        "cityId": "11",
        "districtId": "4",
        "subDistrictId": "5",
        "postalCode": "64151",
        "longitude": 0.0,
        "latitude": 0.0,
        "desa": "Grogol",
        "kecamatan": "Grogol",
        "kota": "Kediri",
        "alamat": "RT.1/RW.11 Jl. Jawa Bedrek Selatan Grogol Kediri, Budrek Selatan, Grogol, Kec. Grogol, Kabupaten Kediri, Jawa Timur 64151, Indonesia"
    },
    {
        "countryId": "ID",
        "provinceId": "11",
        "cityId": "11",
        "districtId": "4",
        "subDistrictId": "5",
        "postalCode": "64151",
        "longitude": 0.0,
        "latitude": 0.0,
        "desa": "Grogol",
        "kecamatan": "Grogol",
        "kota": "Kediri",
        "alamat": "6XX5+PRP, Jl. Jawa, RT.02/RW.02, Budrek Utara, Grogol, Kec. Grogol, Kabupaten Kediri, Jawa Timur 64151, Indonesia"
    },
    {
        "countryId": "ID",
        "provinceId": "11",
        "cityId": "11",
        "districtId": "4",
        "subDistrictId": "9",
        "postalCode": "64151",
        "longitude": 0.0,
        "latitude": 0.0,
        "desa": "Wonoasri",
        "kecamatan": "Grogol",
        "kota": "Kediri",
        "alamat": "RT.9/RW.5 Jl. Gereja No.16, Wonoasri, Kec. Grogol, Kabupaten Kediri, Jawa Timur 64151, Indonesia"
    },
    {
        "countryId": "ID",
        "provinceId": "11",
        "cityId": "11",
        "districtId": "4",
        "subDistrictId": "4",
        "postalCode": "64151",
        "longitude": 0.0,
        "latitude": 0.0,
        "desa": "Gambyok",
        "kecamatan": "Grogol",
        "kota": "Kediri",
        "alamat": "RT.4/RW.6 7X7Q+WQ8, Gambyok, Kec. Grogol, Kabupaten Kediri, Jawa Timur 64151, Indonesia"
    },
    {
        "countryId": "ID",
        "provinceId": "11",
        "cityId": "11",
        "districtId": "4",
        "subDistrictId": "5",
        "postalCode": "64151",
        "longitude": 0.0,
        "latitude": 0.0,
        "desa": "Grogol",
        "kecamatan": "Grogol",
        "kota": "Kediri",
        "alamat": "7X45+MJR, Jl. Raya Kediri - Nganjuk, RT.02/RW.01, Griging Kidul, Grogol, Kec. Grogol, Kabupaten Kediri, Jawa Timur 64151, Indonesia"
    },
    {
        "countryId": "ID",
        "provinceId": "11",
        "cityId": "11",
        "districtId": "4",
        "subDistrictId": "5",
        "postalCode": "64151",
        "longitude": 0.0,
        "latitude": 0.0,
        "desa": "Grogol",
        "kecamatan": "Grogol",
        "kota": "Kediri",
        "alamat": "RT.5/RW.2 6XW5+J6V, Budrek Utara, Grogol, Kec. Grogol, Kabupaten Kediri, Jawa Timur 64151, Indonesia"
    },
    {
        "countryId": "ID",
        "provinceId": "11",
        "cityId": "11",
        "districtId": "4",
        "subDistrictId": "9",
        "postalCode": "64151",
        "longitude": 0.0,
        "latitude": 0.0,
        "desa": "Wonoasri",
        "kecamatan": "Grogol",
        "kota": "Kediri",
        "alamat": "RT.6/RW.1 Jl. Gereja No.16, Wonoasri, Kec. Grogol, Kabupaten Kediri, Jawa Timur 64151, Indonesia"
    },
    {
        "countryId": "ID",
        "provinceId": "11",
        "cityId": "11",
        "districtId": "4",
        "subDistrictId": "4",
        "postalCode": "64151",
        "longitude": 0.0,
        "latitude": 0.0,
        "desa": "Gambyok",
        "kecamatan": "Grogol",
        "kota": "Kediri",
        "alamat": "RT.4/RW.9 7X7Q+WQ8, Gambyok, Kec. Grogol, Kabupaten Kediri, Jawa Timur 64151, Indonesia"
    },
    {
        "countryId": "ID",
        "provinceId": "11",
        "cityId": "11",
        "districtId": "4",
        "subDistrictId": "2",
        "postalCode": "64151",
        "longitude": 0.0,
        "latitude": 0.0,
        "desa": "Cerme",
        "kecamatan": "Grogol",
        "kota": "Kediri",
        "alamat": "RT.1/RW.12 Jl. Raya Gringging No.30, Griging Kidul, Cerme, Kec. Grogol, Kabupaten Kediri, Jawa Timur 64151, Indonesia"
    },
    {
        "countryId": "ID",
        "provinceId": "11",
        "cityId": "11",
        "districtId": "4",
        "subDistrictId": "5",
        "postalCode": "64151",
        "longitude": 0.0,
        "latitude": 0.0,
        "desa": "Grogol",
        "kecamatan": "Grogol",
        "kota": "Kediri",
        "alamat": "RT.1/RW.13 6XW5+J6V, Budrek Utara, Grogol, Kec. Grogol, Kabupaten Kediri, Jawa Timur 64151, Indonesia"
    },
    {
        "countryId": "ID",
        "provinceId": "11",
        "cityId": "11",
        "districtId": "4",
        "subDistrictId": "5",
        "postalCode": "64151",
        "longitude": 0.0,
        "latitude": 0.0,
        "desa": "Grogol",
        "kecamatan": "Grogol",
        "kota": "Kediri",
        "alamat": "RT.2/RW.11 Jl. Jawa No.196, Budrek Utara, Grogol, Kec. Grogol, Kabupaten Kediri, Jawa Timur 64151, Indonesia"
    },
    {
        "countryId": "ID",
        "provinceId": "11",
        "cityId": "11",
        "districtId": "4",
        "subDistrictId": "5",
        "postalCode": "64151",
        "longitude": 0.0,
        "latitude": 0.0,
        "desa": "Grogol",
        "kecamatan": "Grogol",
        "kota": "Kediri",
        "alamat": "RT.1/RW.3 6XV5+P2F, Jl. Jawa Bedrek Selatan Grogol Kediri, Budrek Selatan, Grogol, Kec. Grogol, Kabupaten Kediri, Jawa Timur 64151, Indonesia"
    },
    {
        "countryId": "ID",
        "provinceId": "11",
        "cityId": "11",
        "districtId": "4",
        "subDistrictId": "5",
        "postalCode": "64151",
        "longitude": 0.0,
        "latitude": 0.0,
        "desa": "Grogol",
        "kecamatan": "Grogol",
        "kota": "Kediri",
        "alamat": "RT.1/RW.6 7X26+4WG, Unnamed Road, Semba, Grogol, Kec. Grogol, Kabupaten Kediri, Jawa Timur 64151, Indonesia"
    },
    {
        "countryId": "ID",
        "provinceId": "11",
        "cityId": "11",
        "districtId": "4",
        "subDistrictId": "5",
        "postalCode": "64151",
        "longitude": 0.0,
        "latitude": 0.0,
        "desa": "Grogol",
        "kecamatan": "Grogol",
        "kota": "Kediri",
        "alamat": "RT.7/RW.6 6XW5+MFQ, Budrek Utara, Grogol, Kec. Grogol, Kabupaten Kediri, Jawa Timur 64151, Indonesia"
    },
    {
        "countryId": "ID",
        "provinceId": "11",
        "cityId": "11",
        "districtId": "4",
        "subDistrictId": "2",
        "postalCode": "64151",
        "longitude": 0.0,
        "latitude": 0.0,
        "desa": "Cerme",
        "kecamatan": "Grogol",
        "kota": "Kediri",
        "alamat": "RT.9/RW.3 7X76+R4H, Santren Lor, Cerme, Kec. Grogol, Kediri jawa timur, Jawa Timur 64151, Indonesia"
    }
]